{
  "components": [
    {
      "id": 1,
      "cname": "Foodie",
      "pcomp": "PCODE1",
      "dname": "Foodie_Lekha",
      "isactive": true,
      "compjson": "NA"
    }
  ],
  "definitions": [
    {
      "ctrlgroupname": "Input Controls",
      "groupsequence": 1,
      "ctrlname": "ContactNameField",
      "ctrltype": "text",
      "displayname": "Contact Name",
      "ctrlsize": 6,
      "ctrlwidth": 100,
      "ctrlheight": 100,
      "classname": "form-control",
      "cssstyle": "NA",
      "tooltips": "Please enter your yout name?",
      "placeholder": "Contact Name",
      "isrequired": true,
      "defaultvalue": "NA",
      "isvisible": true,
      "isdisable": true,
      "decimalcount": 0,
      "minlength": 0,
      "maxlength": 0,
      "patterntype": "NA",
      "minnumber": 0,
      "maxnumber": 0,
      "isunique": true,
      "isactive": true,
      "pcomp": "PCODE1",
      "componentid": 1,
      "id": 1
    },
    {
      "ctrlgroupname": "Input Controls",
      "groupsequence": 1,
      "ctrlname": "ContactPhoneField",
      "ctrltype": "number",
      "displayname": "Contact Phone Number",
      "ctrlsize": 6,
      "ctrlwidth": 100,
      "ctrlheight": 100,
      "classname": "form-control",
      "cssstyle": "NA",
      "tooltips": "Please enter your Contact Phone Number?",
      "placeholder": "Contact Phone Number",
      "isrequired": true,
      "defaultvalue": "NA",
      "isvisible": true,
      "isdisable": true,
      "decimalcount": 0,
      "minlength": 0,
      "maxlength": 0,
      "patterntype": "NA",
      "minnumber": 0,
      "maxnumber": 0,
      "isunique": true,
      "isactive": true,
      "pcomp": "PCODE1",
      "componentid": 1,
      "id": 2
    },
    {
      "ctrlgroupname": "Input Controls",
      "groupsequence": 1,
      "ctrlname": "ContactEmailField",
      "ctrltype": "email",
      "displayname": "Contact Email Id",
      "ctrlsize": 6,
      "ctrlwidth": 100,
      "ctrlheight": 100,
      "classname": "form-control",
      "cssstyle": "NA",
      "tooltips": "Please enter your Contact Email Id?",
      "placeholder": "Contact Email Id",
      "isrequired": true,
      "defaultvalue": "NA",
      "isvisible": true,
      "isdisable": true,
      "decimalcount": 0,
      "minlength": 0,
      "maxlength": 0,
      "patterntype": "NA",
      "minnumber": 0,
      "maxnumber": 0,
      "isunique": true,
      "isactive": true,
      "pcomp": "PCODE1",
      "componentid": 1,
      "id": 3
    },
    {
      "ctrlgroupname": "Input Controls",
      "groupsequence": 1,
      "ctrlname": "ordercount",
      "ctrltype": "select",
      "displayname": "Order Count",
      "ctrlsize": 6,
      "ctrlwidth": 100,
      "ctrlheight": 100,
      "classname": "form-control select2bs4",
      "cssstyle": "NA",
      "tooltips": "Please enter your Order Count?",
      "placeholder": "Order Count",
      "isrequired": true,
      "defaultvalue": "NA",
      "isvisible": true,
      "isdisable": true,
      "decimalcount": 0,
      "minlength": 0,
      "maxlength": 0,
      "patterntype": "NA",
      "minnumber": 0,
      "maxnumber": 0,
      "isunique": true,
      "isactive": true,
      "pcomp": "PCODE1",
      "componentid": 1,
      "id": 4
    }
  ],
  "datas": [
    {
      "ContactNameField": "prabha",
      "ContactPhoneField": "56787965432",
      "ContactEmailField": "prabha@gmail.com",
      "ordercount": "3",
      "id": 1
    }
  ]
}
